<?xml version="1.0"?>
<clothinglist>

	<clothing>
		<id>a0405be</id>
		<name>Cardigan </name>
		<price>P100.00 </price>
		<description>Vim ad persecuti appellantur. Eam ignota deterruisset eu, in omnis fierent convenire sed. Ne nulla veritus vel, liber euripidis in eos. Postea comprehensam vis in, detracto deseruisse mei ea. Ex sadipscing deterruisset concludaturque quo.
		</description>
	</clothing>

	<clothing>
		<id>822ad97</id>
		<name>Top + Skirt </name>
		<price>P100.00 </price>
		<description>Black</description>
	</clothing>

	<clothing>
		<id>300a526</id>
		<name> Ringer Dress </name>
		<price> P100.00 </price>
		<description> Color: Maroon</description>
	</clothing>

</clothinglist>